arxml_toys-1.0.1.dist-info/METADATA
arxml_toys-1.0.1.dist-info/RECORD
arxml_toys-1.0.1.dist-info/WHEEL
arxml_toys-1.0.1.dist-info/entry_points.txt
arxml_toys-1.0.1.dist-info/top_level.txt
cli/__init__.py
cli/doc_cli.py
cli/timestamp_cli.py
cli/uuid_cli.py
lib/__init__.py
lib/arxml2xml.py
lib/utils.py
model/__init__.py
model/sw_model.py
