Metadata-Version: 2.1
Name: arxml-toys
Version: 1.0.1
Summary: Power Toys for the ARXML
Home-page: http://github.com/melodypapa/arxml_toys
Author: melodypapa
Author-email: melodypapa@outlook.com
License: MIT
Keywords: AUTOSAR ARXML
Platform: UNKNOWN
Classifier: Development Status :: 1 - Planning
Classifier: Environment :: Console
Classifier: Programming Language :: Python :: 3
Classifier: License :: OSI Approved :: MIT License
Classifier: Operating System :: OS Independent
Requires-Python: >=3.5
Provides-Extra: pytest
License-File: LICENSE
Requires-Dist: armodel
Provides-Extra: pytest
Requires-Dist: pytest-cov; extra == 'pytest'
